{
    "o:label": "Taxon",
    "o:resource_template_property": [
        {
            "o:alternate_label": null,
            "o:alternate_comment": null,
            "o:is_required": false,
            "o:is_private": false,
            "o:default_lang": null,
            "data_types": [],
            "vocabulary_namespace_uri": "http:\/\/rs.tdwg.org\/dwc\/terms\/",
            "vocabulary_label": "DarwinCore",
            "local_name": "TaxonID",
            "label": "Taxon ID"
        },
        {
            "o:alternate_label": null,
            "o:alternate_comment": null,
            "o:is_required": false,
            "o:is_private": false,
            "o:default_lang": null,
            "data_types": [],
            "vocabulary_namespace_uri": "http:\/\/rs.tdwg.org\/dwc\/terms\/",
            "vocabulary_label": "DarwinCore",
            "local_name": "scientificNameID",
            "label": "Scientific Name ID"
        },
        {
            "o:alternate_label": null,
            "o:alternate_comment": null,
            "o:is_required": false,
            "o:is_private": false,
            "o:default_lang": null,
            "data_types": [],
            "vocabulary_namespace_uri": "http:\/\/rs.tdwg.org\/dwc\/terms\/",
            "vocabulary_label": "DarwinCore",
            "local_name": "acceptedNameUsageID",
            "label": "Accepted Name Usage ID"
        },
        {
            "o:alternate_label": null,
            "o:alternate_comment": null,
            "o:is_required": false,
            "o:is_private": false,
            "o:default_lang": null,
            "data_types": [],
            "vocabulary_namespace_uri": "http:\/\/rs.tdwg.org\/dwc\/terms\/",
            "vocabulary_label": "DarwinCore",
            "local_name": "parentNameUsageID",
            "label": "Parent Name Usage ID"
        },
        {
            "o:alternate_label": null,
            "o:alternate_comment": null,
            "o:is_required": false,
            "o:is_private": false,
            "o:default_lang": null,
            "data_types": [],
            "vocabulary_namespace_uri": "http:\/\/rs.tdwg.org\/dwc\/terms\/",
            "vocabulary_label": "DarwinCore",
            "local_name": "originalNameUsageID",
            "label": "Original Name Usage ID"
        },
        {
            "o:alternate_label": null,
            "o:alternate_comment": null,
            "o:is_required": false,
            "o:is_private": false,
            "o:default_lang": null,
            "data_types": [],
            "vocabulary_namespace_uri": "http:\/\/rs.tdwg.org\/dwc\/terms\/",
            "vocabulary_label": "DarwinCore",
            "local_name": "nameAccordingToID",
            "label": "Name According To ID"
        },
        {
            "o:alternate_label": null,
            "o:alternate_comment": null,
            "o:is_required": false,
            "o:is_private": false,
            "o:default_lang": null,
            "data_types": [],
            "vocabulary_namespace_uri": "http:\/\/rs.tdwg.org\/dwc\/terms\/",
            "vocabulary_label": "DarwinCore",
            "local_name": "namePublishedInID",
            "label": "Name Published In ID"
        },
        {
            "o:alternate_label": null,
            "o:alternate_comment": null,
            "o:is_required": false,
            "o:is_private": false,
            "o:default_lang": null,
            "data_types": [],
            "vocabulary_namespace_uri": "http:\/\/rs.tdwg.org\/dwc\/terms\/",
            "vocabulary_label": "DarwinCore",
            "local_name": "taxonConceptID",
            "label": "Taxon Concept ID"
        },
        {
            "o:alternate_label": null,
            "o:alternate_comment": null,
            "o:is_required": false,
            "o:is_private": false,
            "o:default_lang": null,
            "data_types": [],
            "vocabulary_namespace_uri": "http:\/\/rs.tdwg.org\/dwc\/terms\/",
            "vocabulary_label": "DarwinCore",
            "local_name": "scientificName",
            "label": "Scientific Name"
        },
        {
            "o:alternate_label": null,
            "o:alternate_comment": null,
            "o:is_required": false,
            "o:is_private": false,
            "o:default_lang": null,
            "data_types": [],
            "vocabulary_namespace_uri": "http:\/\/rs.tdwg.org\/dwc\/terms\/",
            "vocabulary_label": "DarwinCore",
            "local_name": "acceptedNameUsage",
            "label": "Accepted Name Usage"
        },
        {
            "o:alternate_label": null,
            "o:alternate_comment": null,
            "o:is_required": false,
            "o:is_private": false,
            "o:default_lang": null,
            "data_types": [],
            "vocabulary_namespace_uri": "http:\/\/rs.tdwg.org\/dwc\/terms\/",
            "vocabulary_label": "DarwinCore",
            "local_name": "parentNameUsage",
            "label": "Parent Name Usage"
        },
        {
            "o:alternate_label": null,
            "o:alternate_comment": null,
            "o:is_required": false,
            "o:is_private": false,
            "o:default_lang": null,
            "data_types": [],
            "vocabulary_namespace_uri": "http:\/\/rs.tdwg.org\/dwc\/terms\/",
            "vocabulary_label": "DarwinCore",
            "local_name": "originalNameUsage",
            "label": "Original Name Usage"
        },
        {
            "o:alternate_label": null,
            "o:alternate_comment": null,
            "o:is_required": false,
            "o:is_private": false,
            "o:default_lang": null,
            "data_types": [],
            "vocabulary_namespace_uri": "http:\/\/rs.tdwg.org\/dwc\/terms\/",
            "vocabulary_label": "DarwinCore",
            "local_name": "nameAccordingTo",
            "label": "Name According To"
        },
        {
            "o:alternate_label": null,
            "o:alternate_comment": null,
            "o:is_required": false,
            "o:is_private": false,
            "o:default_lang": null,
            "data_types": [],
            "vocabulary_namespace_uri": "http:\/\/rs.tdwg.org\/dwc\/terms\/",
            "vocabulary_label": "DarwinCore",
            "local_name": "namePublishedIn",
            "label": "Name Published In"
        },
        {
            "o:alternate_label": null,
            "o:alternate_comment": null,
            "o:is_required": false,
            "o:is_private": false,
            "o:default_lang": null,
            "data_types": [],
            "vocabulary_namespace_uri": "http:\/\/rs.tdwg.org\/dwc\/terms\/",
            "vocabulary_label": "DarwinCore",
            "local_name": "namePublishedInYear",
            "label": "Name Published In Year"
        },
        {
            "o:alternate_label": null,
            "o:alternate_comment": null,
            "o:is_required": false,
            "o:is_private": false,
            "o:default_lang": null,
            "data_types": [],
            "vocabulary_namespace_uri": "http:\/\/rs.tdwg.org\/dwc\/terms\/",
            "vocabulary_label": "DarwinCore",
            "local_name": "higherClassification",
            "label": "Higher Classification"
        },
        {
            "o:alternate_label": null,
            "o:alternate_comment": null,
            "o:is_required": false,
            "o:is_private": false,
            "o:default_lang": null,
            "data_types": [],
            "vocabulary_namespace_uri": "http:\/\/rs.tdwg.org\/dwc\/terms\/",
            "vocabulary_label": "DarwinCore",
            "local_name": "kingdom",
            "label": "Kingdom"
        },
        {
            "o:alternate_label": null,
            "o:alternate_comment": null,
            "o:is_required": false,
            "o:is_private": false,
            "o:default_lang": null,
            "data_types": [],
            "vocabulary_namespace_uri": "http:\/\/rs.tdwg.org\/dwc\/terms\/",
            "vocabulary_label": "DarwinCore",
            "local_name": "phylum",
            "label": "Phylum"
        },
        {
            "o:alternate_label": null,
            "o:alternate_comment": null,
            "o:is_required": false,
            "o:is_private": false,
            "o:default_lang": null,
            "data_types": [],
            "vocabulary_namespace_uri": "http:\/\/rs.tdwg.org\/dwc\/terms\/",
            "vocabulary_label": "DarwinCore",
            "local_name": "class",
            "label": "Class"
        },
        {
            "o:alternate_label": null,
            "o:alternate_comment": null,
            "o:is_required": false,
            "o:is_private": false,
            "o:default_lang": null,
            "data_types": [],
            "vocabulary_namespace_uri": "http:\/\/rs.tdwg.org\/dwc\/terms\/",
            "vocabulary_label": "DarwinCore",
            "local_name": "order",
            "label": "Order"
        },
        {
            "o:alternate_label": null,
            "o:alternate_comment": null,
            "o:is_required": false,
            "o:is_private": false,
            "o:default_lang": null,
            "data_types": [],
            "vocabulary_namespace_uri": "http:\/\/rs.tdwg.org\/dwc\/terms\/",
            "vocabulary_label": "DarwinCore",
            "local_name": "superfamily",
            "label": "Superfamily"
        },
        {
            "o:alternate_label": null,
            "o:alternate_comment": null,
            "o:is_required": false,
            "o:is_private": false,
            "o:default_lang": null,
            "data_types": [],
            "vocabulary_namespace_uri": "http:\/\/rs.tdwg.org\/dwc\/terms\/",
            "vocabulary_label": "DarwinCore",
            "local_name": "family",
            "label": "Family"
        },
        {
            "o:alternate_label": null,
            "o:alternate_comment": null,
            "o:is_required": false,
            "o:is_private": false,
            "o:default_lang": null,
            "data_types": [],
            "vocabulary_namespace_uri": "http:\/\/rs.tdwg.org\/dwc\/terms\/",
            "vocabulary_label": "DarwinCore",
            "local_name": "subfamily",
            "label": "Subfamily"
        },
        {
            "o:alternate_label": null,
            "o:alternate_comment": null,
            "o:is_required": false,
            "o:is_private": false,
            "o:default_lang": null,
            "data_types": [],
            "vocabulary_namespace_uri": "http:\/\/rs.tdwg.org\/dwc\/terms\/",
            "vocabulary_label": "DarwinCore",
            "local_name": "tribe",
            "label": "Tribe"
        },
        {
            "o:alternate_label": null,
            "o:alternate_comment": null,
            "o:is_required": false,
            "o:is_private": false,
            "o:default_lang": null,
            "data_types": [],
            "vocabulary_namespace_uri": "http:\/\/rs.tdwg.org\/dwc\/terms\/",
            "vocabulary_label": "DarwinCore",
            "local_name": "subtribe",
            "label": "Subtribe"
        },
        {
            "o:alternate_label": null,
            "o:alternate_comment": null,
            "o:is_required": false,
            "o:is_private": false,
            "o:default_lang": null,
            "data_types": [],
            "vocabulary_namespace_uri": "http:\/\/rs.tdwg.org\/dwc\/terms\/",
            "vocabulary_label": "DarwinCore",
            "local_name": "genus",
            "label": "Genus"
        },
        {
            "o:alternate_label": null,
            "o:alternate_comment": null,
            "o:is_required": false,
            "o:is_private": false,
            "o:default_lang": null,
            "data_types": [],
            "vocabulary_namespace_uri": "http:\/\/rs.tdwg.org\/dwc\/terms\/",
            "vocabulary_label": "DarwinCore",
            "local_name": "genericName",
            "label": "Generic Name"
        },
        {
            "o:alternate_label": null,
            "o:alternate_comment": null,
            "o:is_required": false,
            "o:is_private": false,
            "o:default_lang": null,
            "data_types": [],
            "vocabulary_namespace_uri": "http:\/\/rs.tdwg.org\/dwc\/terms\/",
            "vocabulary_label": "DarwinCore",
            "local_name": "subgenus",
            "label": "Subgenus"
        },
        {
            "o:alternate_label": null,
            "o:alternate_comment": null,
            "o:is_required": false,
            "o:is_private": false,
            "o:default_lang": null,
            "data_types": [],
            "vocabulary_namespace_uri": "http:\/\/rs.tdwg.org\/dwc\/terms\/",
            "vocabulary_label": "DarwinCore",
            "local_name": "infragenericEpithet",
            "label": "Infrageneric Epithet"
        },
        {
            "o:alternate_label": null,
            "o:alternate_comment": null,
            "o:is_required": false,
            "o:is_private": false,
            "o:default_lang": null,
            "data_types": [],
            "vocabulary_namespace_uri": "http:\/\/rs.tdwg.org\/dwc\/terms\/",
            "vocabulary_label": "DarwinCore",
            "local_name": "specificEpithet",
            "label": "Specific Epithet"
        },
        {
            "o:alternate_label": null,
            "o:alternate_comment": null,
            "o:is_required": false,
            "o:is_private": false,
            "o:default_lang": null,
            "data_types": [],
            "vocabulary_namespace_uri": "http:\/\/rs.tdwg.org\/dwc\/terms\/",
            "vocabulary_label": "DarwinCore",
            "local_name": "infraspecificEpithet",
            "label": "Infraspecific Epithet"
        },
        {
            "o:alternate_label": null,
            "o:alternate_comment": null,
            "o:is_required": false,
            "o:is_private": false,
            "o:default_lang": null,
            "data_types": [],
            "vocabulary_namespace_uri": "http:\/\/rs.tdwg.org\/dwc\/terms\/",
            "vocabulary_label": "DarwinCore",
            "local_name": "cultivarEpithet",
            "label": "Cultivar Epithet"
        },
        {
            "o:alternate_label": null,
            "o:alternate_comment": null,
            "o:is_required": false,
            "o:is_private": false,
            "o:default_lang": null,
            "data_types": [],
            "vocabulary_namespace_uri": "https:\/\/schema.org",
            "vocabulary_label": "Schema.org",
            "local_name": "taxonRank",
            "label": "taxonRank"
        },
        {
            "o:alternate_label": null,
            "o:alternate_comment": null,
            "o:is_required": false,
            "o:is_private": false,
            "o:default_lang": null,
            "data_types": [],
            "vocabulary_namespace_uri": "http:\/\/rs.tdwg.org\/dwc\/terms\/",
            "vocabulary_label": "DarwinCore",
            "local_name": "verbatimTaxonRank",
            "label": "Verbatim Taxon Rank"
        },
        {
            "o:alternate_label": null,
            "o:alternate_comment": null,
            "o:is_required": false,
            "o:is_private": false,
            "o:default_lang": null,
            "data_types": [],
            "vocabulary_namespace_uri": "http:\/\/rs.tdwg.org\/dwc\/terms\/",
            "vocabulary_label": "DarwinCore",
            "local_name": "scientificNameAuthorship",
            "label": "Scientific Name Authorship"
        },
        {
            "o:alternate_label": null,
            "o:alternate_comment": null,
            "o:is_required": false,
            "o:is_private": false,
            "o:default_lang": null,
            "data_types": [],
            "vocabulary_namespace_uri": "http:\/\/rs.tdwg.org\/dwc\/terms\/",
            "vocabulary_label": "DarwinCore",
            "local_name": "vernacularName",
            "label": "Vernacular Name"
        },
        {
            "o:alternate_label": null,
            "o:alternate_comment": null,
            "o:is_required": false,
            "o:is_private": false,
            "o:default_lang": null,
            "data_types": [],
            "vocabulary_namespace_uri": "http:\/\/rs.tdwg.org\/dwc\/terms\/",
            "vocabulary_label": "DarwinCore",
            "local_name": "nomenclaturalCode",
            "label": "Nomenclatural Code"
        },
        {
            "o:alternate_label": null,
            "o:alternate_comment": null,
            "o:is_required": false,
            "o:is_private": false,
            "o:default_lang": null,
            "data_types": [],
            "vocabulary_namespace_uri": "http:\/\/rs.tdwg.org\/dwc\/terms\/",
            "vocabulary_label": "DarwinCore",
            "local_name": "taxonomicStatus",
            "label": "Taxonomic Status"
        },
        {
            "o:alternate_label": null,
            "o:alternate_comment": null,
            "o:is_required": false,
            "o:is_private": false,
            "o:default_lang": null,
            "data_types": [],
            "vocabulary_namespace_uri": "http:\/\/rs.tdwg.org\/dwc\/terms\/",
            "vocabulary_label": "DarwinCore",
            "local_name": "nomenclaturalStatus",
            "label": "Nomenclatural Status"
        },
        {
            "o:alternate_label": null,
            "o:alternate_comment": null,
            "o:is_required": false,
            "o:is_private": false,
            "o:default_lang": null,
            "data_types": [],
            "vocabulary_namespace_uri": "http:\/\/rs.tdwg.org\/dwc\/terms\/",
            "vocabulary_label": "DarwinCore",
            "local_name": "taxonRemarks",
            "label": "Taxon Remarks"
        }
    ],
    "o:resource_class": {
        "vocabulary_namespace_uri": "http:\/\/rs.tdwg.org\/dwc\/terms\/",
        "vocabulary_label": "DarwinCore",
        "local_name": "Taxon",
        "label": "Taxon"
    }
}